{
  "type": "minecraft:crafting_shapeless",
  "ingredients": [
    {
      "item": "minecraft:experience_bottle"
    },
    {
      "item": "minecraft:experience_bottle"
    },
    {
      "item": "minecraft:experience_bottle"
    },
    {
      "item": "minecraft:lapis_lazuli"
    },
    {
      "item": "minecraft:lapis_lazuli"
    },
    {
      "item": "minecraft:cobweb"
    },
    {
      "item": "minecraft:cobweb"
    },
    {
      "item": "minecraft:cobweb"
    },
    {
      "item": "minecraft:book"
    }
  ],
  "result": {
    "id": "minecraft:enchanted_book",
    "components": {
      "minecraft:enchantments": {
        "minecraft:bane_of_arthropods": 1
      }
    }
  }
}
